{
  "language": "powerquery",
  "highlights": {
    "let": {
      "kind": 0,
      "description": "Highlights all occurrences of 'let'"
    },
    "in": {
      "kind": 0,
      "description": "Highlights all occurrences of 'in'"
    },
    "if": {
      "kind": 0,
      "description": "Highlights all occurrences of 'if'"
    },
    "then": {
      "kind": 0,
      "description": "Highlights all occurrences of 'then'"
    },
    "else": {
      "kind": 0,
      "description": "Highlights all occurrences of 'else'"
    },
    "each": {
      "kind": 0,
      "description": "Highlights all occurrences of 'each'"
    },
    "try": {
      "kind": 0,
      "description": "Highlights all occurrences of 'try'"
    },
    "otherwise": {
      "kind": 0,
      "description": "Highlights all occurrences of 'otherwise'"
    },
    "error": {
      "kind": 0,
      "description": "Highlights all occurrences of 'error'"
    },
    "as": {
      "kind": 0,
      "description": "Highlights all occurrences of 'as'"
    },
    "is": {
      "kind": 0,
      "description": "Highlights all occurrences of 'is'"
    },
    "type": {
      "kind": 0,
      "description": "Highlights all occurrences of 'type'"
    },
    "section": {
      "kind": 0,
      "description": "Highlights all occurrences of 'section'"
    },
    "shared": {
      "kind": 0,
      "description": "Highlights all occurrences of 'shared'"
    },
    "query": {
      "kind": 0,
      "description": "Highlights all occurrences of 'query'"
    },
    "null": {
      "kind": 0,
      "description": "Highlights all occurrences of 'null'"
    },
    "true": {
      "kind": 0,
      "description": "Highlights all occurrences of 'true'"
    },
    "false": {
      "kind": 0,
      "description": "Highlights all occurrences of 'false'"
    },
    "and": {
      "kind": 0,
      "description": "Highlights all occurrences of 'and'"
    },
    "or": {
      "kind": 0,
      "description": "Highlights all occurrences of 'or'"
    },
    "not": {
      "kind": 0,
      "description": "Highlights all occurrences of 'not'"
    },
    "meta": {
      "kind": 0,
      "description": "Highlights all occurrences of 'meta'"
    },
    "#date": {
      "kind": 0,
      "description": "Highlights all occurrences of '#date'"
    },
    "#datetime": {
      "kind": 0,
      "description": "Highlights all occurrences of '#datetime'"
    },
    "#datetimezone": {
      "kind": 0,
      "description": "Highlights all occurrences of '#datetimezone'"
    },
    "#duration": {
      "kind": 0,
      "description": "Highlights all occurrences of '#duration'"
    },
    "#time": {
      "kind": 0,
      "description": "Highlights all occurrences of '#time'"
    },
    "#infinity": {
      "kind": 0,
      "description": "Highlights all occurrences of '#infinity'"
    },
    "#nan": {
      "kind": 0,
      "description": "Highlights all occurrences of '#nan'"
    },
    "#sections": {
      "kind": 0,
      "description": "Highlights all occurrences of '#sections'"
    },
    "#shared": {
      "kind": 0,
      "description": "Highlights all occurrences of '#shared'"
    },
    "#binary": {
      "kind": 0,
      "description": "Highlights all occurrences of '#binary'"
    },
    "#table": {
      "kind": 0,
      "description": "Highlights all occurrences of '#table'"
    },
    "#list": {
      "kind": 0,
      "description": "Highlights all occurrences of '#list'"
    },
    "Record": {
      "kind": 0,
      "description": "Highlights all occurrences of 'Record'"
    },
    "Table": {
      "kind": 0,
      "description": "Highlights all occurrences of 'Table'"
    },
    "List": {
      "kind": 0,
      "description": "Highlights all occurrences of 'List'"
    },
    "Text": {
      "kind": 0,
      "description": "Highlights all occurrences of 'Text'"
    },
    "Number": {
      "kind": 0,
      "description": "Highlights all occurrences of 'Number'"
    },
    "Date": {
      "kind": 0,
      "description": "Highlights all occurrences of 'Date'"
    },
    "Time": {
      "kind": 0,
      "description": "Highlights all occurrences of 'Time'"
    },
    "DateTime": {
      "kind": 0,
      "description": "Highlights all occurrences of 'DateTime'"
    },
    "DateTimeZone": {
      "kind": 0,
      "description": "Highlights all occurrences of 'DateTimeZone'"
    },
    "Duration": {
      "kind": 0,
      "description": "Highlights all occurrences of 'Duration'"
    },
    "Binary": {
      "kind": 0,
      "description": "Highlights all occurrences of 'Binary'"
    },
    "Type": {
      "kind": 0,
      "description": "Highlights all occurrences of 'Type'"
    },
    "Function": {
      "kind": 0,
      "description": "Highlights all occurrences of 'Function'"
    },
    "Logical": {
      "kind": 0,
      "description": "Highlights all occurrences of 'Logical'"
    },
    "Error": {
      "kind": 0,
      "description": "Highlights all occurrences of 'Error'"
    },
    "Action": {
      "kind": 0,
      "description": "Highlights all occurrences of 'Action'"
    },
    "Any": {
      "kind": 0,
      "description": "Highlights all occurrences of 'Any'"
    },
    "None": {
      "kind": 0,
      "description": "Highlights all occurrences of 'None'"
    }
  },
  "bracketPairs": [],
  "keywordGroups": [
    {
      "name": "keywords",
      "keywords": [
        "let",
        "in",
        "if",
        "then",
        "else",
        "each",
        "try",
        "otherwise",
        "error",
        "and",
        "or",
        "not",
        "true",
        "false",
        "null",
        "type",
        "as",
        "is",
        "section",
        "shared"
      ],
      "highlightKind": 0
    }
  ]
}