{
  "language": "makefile",
  "declarations": {
    "wildcard": {
      "signature": "wildcard",
      "description": "Built-in: wildcard",
      "type": "function",
      "module": "builtin"
    },
    "patsubst": {
      "signature": "patsubst",
      "description": "Built-in: patsubst",
      "type": "function",
      "module": "builtin"
    },
    "subst": {
      "signature": "subst",
      "description": "Built-in: subst",
      "type": "function",
      "module": "builtin"
    },
    "strip": {
      "signature": "strip",
      "description": "Built-in: strip",
      "type": "function",
      "module": "builtin"
    },
    "findstring": {
      "signature": "findstring",
      "description": "Built-in: findstring",
      "type": "function",
      "module": "builtin"
    },
    "filter": {
      "signature": "filter",
      "description": "Built-in: filter",
      "type": "function",
      "module": "builtin"
    },
    "filter-out": {
      "signature": "filter-out",
      "description": "Built-in: filter-out",
      "type": "function",
      "module": "builtin"
    },
    "sort": {
      "signature": "sort",
      "description": "Built-in: sort",
      "type": "function",
      "module": "builtin"
    },
    "word": {
      "signature": "word",
      "description": "Built-in: word",
      "type": "function",
      "module": "builtin"
    },
    "wordlist": {
      "signature": "wordlist",
      "description": "Built-in: wordlist",
      "type": "function",
      "module": "builtin"
    },
    "words": {
      "signature": "words",
      "description": "Built-in: words",
      "type": "function",
      "module": "builtin"
    },
    "firstword": {
      "signature": "firstword",
      "description": "Built-in: firstword",
      "type": "function",
      "module": "builtin"
    },
    "lastword": {
      "signature": "lastword",
      "description": "Built-in: lastword",
      "type": "function",
      "module": "builtin"
    },
    "dir": {
      "signature": "dir",
      "description": "Built-in: dir",
      "type": "function",
      "module": "builtin"
    },
    "notdir": {
      "signature": "notdir",
      "description": "Built-in: notdir",
      "type": "function",
      "module": "builtin"
    },
    "suffix": {
      "signature": "suffix",
      "description": "Built-in: suffix",
      "type": "function",
      "module": "builtin"
    },
    "basename": {
      "signature": "basename",
      "description": "Built-in: basename",
      "type": "function",
      "module": "builtin"
    },
    "addsuffix": {
      "signature": "addsuffix",
      "description": "Built-in: addsuffix",
      "type": "function",
      "module": "builtin"
    },
    "addprefix": {
      "signature": "addprefix",
      "description": "Built-in: addprefix",
      "type": "function",
      "module": "builtin"
    },
    "join": {
      "signature": "join",
      "description": "Built-in: join",
      "type": "function",
      "module": "builtin"
    },
    "realpath": {
      "signature": "realpath",
      "description": "Built-in: realpath",
      "type": "function",
      "module": "builtin"
    },
    "abspath": {
      "signature": "abspath",
      "description": "Built-in: abspath",
      "type": "function",
      "module": "builtin"
    },
    "foreach": {
      "signature": "foreach",
      "description": "Built-in: foreach",
      "type": "function",
      "module": "builtin"
    },
    "if": {
      "signature": "if",
      "description": "Built-in: if",
      "type": "function",
      "module": "builtin"
    },
    "or": {
      "signature": "or",
      "description": "Built-in: or",
      "type": "function",
      "module": "builtin"
    },
    "and": {
      "signature": "and",
      "description": "Built-in: and",
      "type": "function",
      "module": "builtin"
    },
    "call": {
      "signature": "call",
      "description": "Built-in: call",
      "type": "function",
      "module": "builtin"
    },
    "value": {
      "signature": "value",
      "description": "Built-in: value",
      "type": "function",
      "module": "builtin"
    },
    "eval": {
      "signature": "eval",
      "description": "Built-in: eval",
      "type": "function",
      "module": "builtin"
    },
    "origin": {
      "signature": "origin",
      "description": "Built-in: origin",
      "type": "function",
      "module": "builtin"
    }
  },
  "declarationPatterns": [
    {
      "name": "Target",
      "pattern": "^([a-zA-Z_][a-zA-Z0-9_./-]*)\\\\s*:",
      "captureGroup": 1,
      "type": "function"
    },
    {
      "name": "Variable",
      "pattern": "^\\\\s*([A-Z_][A-Z0-9_]*)\\\\s*[:?+]?=",
      "captureGroup": 1,
      "type": "variable"
    }
  ]
}
