{
  "language": "docker-compose",
  "autoFormatTriggerCharacters": ["\n", "="],
  "formatRules": [
    {
      "trigger": "=",
      "description": "Format around equals sign in environment variable definitions",
      "rules": [
        {
          "action": "trimWhitespace",
          "pattern": "\\s+=",
          "description": "Normalize whitespace before equals"
        }
      ]
    },
    {
      "trigger": "\n",
      "description": "Auto-indent based on YAML-like docker-compose structure",
      "rules": [
        {
          "action": "indent",
          "pattern": ":\\s*$",
          "description": "Indent after key with no inline value"
        },
        {
          "action": "indent",
          "pattern": "^\\s*-\\s+.*:\\s*$",
          "description": "Indent after list item with nested mapping"
        },
        {
          "action": "trimWhitespace",
          "pattern": "\\s+$",
          "description": "Remove trailing whitespace"
        }
      ]
    }
  ],
  "indentation": {
    "increasePattern": "^\\s*\\S+.*:\\s*$",
    "decreasePattern": "^\\s*$"
  }
}