{
  "language": "restructuredtext",
  "completions": [
    {
      "label": ".. note::",
      "kind": 17,
      "detail": "keyword .. note::",
      "documentation": {
        "value": ".. note:: keyword"
      },
      "insertText": ".. note::",
      "sortText": "00_kw",
      "insertTextRules": 0
    },
    {
      "label": ".. warning::",
      "kind": 17,
      "detail": "keyword .. warning::",
      "documentation": {
        "value": ".. warning:: keyword"
      },
      "insertText": ".. warning::",
      "sortText": "00_kw",
      "insertTextRules": 0
    },
    {
      "label": ".. tip::",
      "kind": 17,
      "detail": "keyword .. tip::",
      "documentation": {
        "value": ".. tip:: keyword"
      },
      "insertText": ".. tip::",
      "sortText": "00_kw",
      "insertTextRules": 0
    },
    {
      "label": ".. important::",
      "kind": 17,
      "detail": "keyword .. important::",
      "documentation": {
        "value": ".. important:: keyword"
      },
      "insertText": ".. important::",
      "sortText": "00_kw",
      "insertTextRules": 0
    },
    {
      "label": ".. danger::",
      "kind": 17,
      "detail": "keyword .. danger::",
      "documentation": {
        "value": ".. danger:: keyword"
      },
      "insertText": ".. danger::",
      "sortText": "00_kw",
      "insertTextRules": 0
    },
    {
      "label": ".. error::",
      "kind": 17,
      "detail": "keyword .. error::",
      "documentation": {
        "value": ".. error:: keyword"
      },
      "insertText": ".. error::",
      "sortText": "00_kw",
      "insertTextRules": 0
    },
    {
      "label": ".. hint::",
      "kind": 17,
      "detail": "keyword .. hint::",
      "documentation": {
        "value": ".. hint:: keyword"
      },
      "insertText": ".. hint::",
      "sortText": "00_kw",
      "insertTextRules": 0
    },
    {
      "label": ".. caution::",
      "kind": 17,
      "detail": "keyword .. caution::",
      "documentation": {
        "value": ".. caution:: keyword"
      },
      "insertText": ".. caution::",
      "sortText": "00_kw",
      "insertTextRules": 0
    },
    {
      "label": ".. attention::",
      "kind": 17,
      "detail": "keyword .. attention::",
      "documentation": {
        "value": ".. attention:: keyword"
      },
      "insertText": ".. attention::",
      "sortText": "00_kw",
      "insertTextRules": 0
    },
    {
      "label": ".. seealso::",
      "kind": 17,
      "detail": "keyword .. seealso::",
      "documentation": {
        "value": ".. seealso:: keyword"
      },
      "insertText": ".. seealso::",
      "sortText": "00_kw",
      "insertTextRules": 0
    },
    {
      "label": ".. code-block::",
      "kind": 17,
      "detail": "keyword .. code-block::",
      "documentation": {
        "value": ".. code-block:: keyword"
      },
      "insertText": ".. code-block::",
      "sortText": "00_kw",
      "insertTextRules": 0
    },
    {
      "label": ".. image::",
      "kind": 17,
      "detail": "keyword .. image::",
      "documentation": {
        "value": ".. image:: keyword"
      },
      "insertText": ".. image::",
      "sortText": "00_kw",
      "insertTextRules": 0
    },
    {
      "label": ".. figure::",
      "kind": 17,
      "detail": "keyword .. figure::",
      "documentation": {
        "value": ".. figure:: keyword"
      },
      "insertText": ".. figure::",
      "sortText": "00_kw",
      "insertTextRules": 0
    },
    {
      "label": ".. table::",
      "kind": 17,
      "detail": "keyword .. table::",
      "documentation": {
        "value": ".. table:: keyword"
      },
      "insertText": ".. table::",
      "sortText": "00_kw",
      "insertTextRules": 0
    },
    {
      "label": ".. list-table::",
      "kind": 17,
      "detail": "keyword .. list-table::",
      "documentation": {
        "value": ".. list-table:: keyword"
      },
      "insertText": ".. list-table::",
      "sortText": "00_kw",
      "insertTextRules": 0
    },
    {
      "label": ".. toctree::",
      "kind": 17,
      "detail": "keyword .. toctree::",
      "documentation": {
        "value": ".. toctree:: keyword"
      },
      "insertText": ".. toctree::",
      "sortText": "00_kw",
      "insertTextRules": 0
    },
    {
      "label": ".. include::",
      "kind": 17,
      "detail": "keyword .. include::",
      "documentation": {
        "value": ".. include:: keyword"
      },
      "insertText": ".. include::",
      "sortText": "00_kw",
      "insertTextRules": 0
    },
    {
      "label": ".. literalinclude::",
      "kind": 17,
      "detail": "keyword .. literalinclude::",
      "documentation": {
        "value": ".. literalinclude:: keyword"
      },
      "insertText": ".. literalinclude::",
      "sortText": "00_kw",
      "insertTextRules": 0
    },
    {
      "label": ".. contents::",
      "kind": 17,
      "detail": "keyword .. contents::",
      "documentation": {
        "value": ".. contents:: keyword"
      },
      "insertText": ".. contents::",
      "sortText": "00_kw",
      "insertTextRules": 0
    },
    {
      "label": ".. index::",
      "kind": 17,
      "detail": "keyword .. index::",
      "documentation": {
        "value": ".. index:: keyword"
      },
      "insertText": ".. index::",
      "sortText": "00_kw",
      "insertTextRules": 0
    },
    {
      "label": ".. highlight::",
      "kind": 17,
      "detail": "keyword .. highlight::",
      "documentation": {
        "value": ".. highlight:: keyword"
      },
      "insertText": ".. highlight::",
      "sortText": "00_kw",
      "insertTextRules": 0
    },
    {
      "label": ".. raw::",
      "kind": 17,
      "detail": "keyword .. raw::",
      "documentation": {
        "value": ".. raw:: keyword"
      },
      "insertText": ".. raw::",
      "sortText": "00_kw",
      "insertTextRules": 0
    },
    {
      "label": ".. role::",
      "kind": 17,
      "detail": "keyword .. role::",
      "documentation": {
        "value": ".. role:: keyword"
      },
      "insertText": ".. role::",
      "sortText": "00_kw",
      "insertTextRules": 0
    },
    {
      "label": ".. default-role::",
      "kind": 17,
      "detail": "keyword .. default-role::",
      "documentation": {
        "value": ".. default-role:: keyword"
      },
      "insertText": ".. default-role::",
      "sortText": "00_kw",
      "insertTextRules": 0
    },
    {
      "label": ".. class::",
      "kind": 17,
      "detail": "keyword .. class::",
      "documentation": {
        "value": ".. class:: keyword"
      },
      "insertText": ".. class::",
      "sortText": "00_kw",
      "insertTextRules": 0
    },
    {
      "label": ":ref:",
      "kind": 1,
      "detail": "builtin :ref:",
      "documentation": {
        "value": "Built-in: :ref:"
      },
      "insertText": ":ref:",
      "sortText": "01_bi",
      "insertTextRules": 0
    },
    {
      "label": ":doc:",
      "kind": 1,
      "detail": "builtin :doc:",
      "documentation": {
        "value": "Built-in: :doc:"
      },
      "insertText": ":doc:",
      "sortText": "01_bi",
      "insertTextRules": 0
    },
    {
      "label": ":func:",
      "kind": 1,
      "detail": "builtin :func:",
      "documentation": {
        "value": "Built-in: :func:"
      },
      "insertText": ":func:",
      "sortText": "01_bi",
      "insertTextRules": 0
    },
    {
      "label": ":class:",
      "kind": 1,
      "detail": "builtin :class:",
      "documentation": {
        "value": "Built-in: :class:"
      },
      "insertText": ":class:",
      "sortText": "01_bi",
      "insertTextRules": 0
    },
    {
      "label": ":meth:",
      "kind": 1,
      "detail": "builtin :meth:",
      "documentation": {
        "value": "Built-in: :meth:"
      },
      "insertText": ":meth:",
      "sortText": "01_bi",
      "insertTextRules": 0
    },
    {
      "label": ":attr:",
      "kind": 1,
      "detail": "builtin :attr:",
      "documentation": {
        "value": "Built-in: :attr:"
      },
      "insertText": ":attr:",
      "sortText": "01_bi",
      "insertTextRules": 0
    },
    {
      "label": ":mod:",
      "kind": 1,
      "detail": "builtin :mod:",
      "documentation": {
        "value": "Built-in: :mod:"
      },
      "insertText": ":mod:",
      "sortText": "01_bi",
      "insertTextRules": 0
    },
    {
      "label": ":data:",
      "kind": 1,
      "detail": "builtin :data:",
      "documentation": {
        "value": "Built-in: :data:"
      },
      "insertText": ":data:",
      "sortText": "01_bi",
      "insertTextRules": 0
    },
    {
      "label": ":const:",
      "kind": 1,
      "detail": "builtin :const:",
      "documentation": {
        "value": "Built-in: :const:"
      },
      "insertText": ":const:",
      "sortText": "01_bi",
      "insertTextRules": 0
    },
    {
      "label": ":exc:",
      "kind": 1,
      "detail": "builtin :exc:",
      "documentation": {
        "value": "Built-in: :exc:"
      },
      "insertText": ":exc:",
      "sortText": "01_bi",
      "insertTextRules": 0
    },
    {
      "label": ":type:",
      "kind": 1,
      "detail": "builtin :type:",
      "documentation": {
        "value": "Built-in: :type:"
      },
      "insertText": ":type:",
      "sortText": "01_bi",
      "insertTextRules": 0
    },
    {
      "label": ":term:",
      "kind": 1,
      "detail": "builtin :term:",
      "documentation": {
        "value": "Built-in: :term:"
      },
      "insertText": ":term:",
      "sortText": "01_bi",
      "insertTextRules": 0
    },
    {
      "label": ":abbr:",
      "kind": 1,
      "detail": "builtin :abbr:",
      "documentation": {
        "value": "Built-in: :abbr:"
      },
      "insertText": ":abbr:",
      "sortText": "01_bi",
      "insertTextRules": 0
    },
    {
      "label": ":command:",
      "kind": 1,
      "detail": "builtin :command:",
      "documentation": {
        "value": "Built-in: :command:"
      },
      "insertText": ":command:",
      "sortText": "01_bi",
      "insertTextRules": 0
    },
    {
      "label": ":file:",
      "kind": 1,
      "detail": "builtin :file:",
      "documentation": {
        "value": "Built-in: :file:"
      },
      "insertText": ":file:",
      "sortText": "01_bi",
      "insertTextRules": 0
    },
    {
      "label": ":guilabel:",
      "kind": 1,
      "detail": "builtin :guilabel:",
      "documentation": {
        "value": "Built-in: :guilabel:"
      },
      "insertText": ":guilabel:",
      "sortText": "01_bi",
      "insertTextRules": 0
    },
    {
      "label": ":kbd:",
      "kind": 1,
      "detail": "builtin :kbd:",
      "documentation": {
        "value": "Built-in: :kbd:"
      },
      "insertText": ":kbd:",
      "sortText": "01_bi",
      "insertTextRules": 0
    },
    {
      "label": ":menuselection:",
      "kind": 1,
      "detail": "builtin :menuselection:",
      "documentation": {
        "value": "Built-in: :menuselection:"
      },
      "insertText": ":menuselection:",
      "sortText": "01_bi",
      "insertTextRules": 0
    },
    {
      "label": ":program:",
      "kind": 1,
      "detail": "builtin :program:",
      "documentation": {
        "value": "Built-in: :program:"
      },
      "insertText": ":program:",
      "sortText": "01_bi",
      "insertTextRules": 0
    },
    {
      "label": ":samp:",
      "kind": 1,
      "detail": "builtin :samp:",
      "documentation": {
        "value": "Built-in: :samp:"
      },
      "insertText": ":samp:",
      "sortText": "01_bi",
      "insertTextRules": 0
    },
    {
      "label": "code_block",
      "kind": 14,
      "detail": "snippet Code block",
      "documentation": {
        "value": "Code block directive"
      },
      "insertText": ".. code-block:: ${1:python}\n\n   ${0}",
      "insertTextRules": 4,
      "sortText": "03_snip"
    },
    {
      "label": "image",
      "kind": 14,
      "detail": "snippet Image",
      "documentation": {
        "value": "Image directive"
      },
      "insertText": ".. image:: ${1:path/to/image.png}\n   :alt: ${2:alt text}\n   :width: ${3:400px}",
      "insertTextRules": 4,
      "sortText": "03_snip"
    },
    {
      "label": "toctree",
      "kind": 14,
      "detail": "snippet Table of Contents",
      "documentation": {
        "value": "Toctree directive"
      },
      "insertText": ".. toctree::\n   :maxdepth: ${1:2}\n   :caption: ${2:Contents}\n\n   ${0}",
      "insertTextRules": 4,
      "sortText": "03_snip"
    },
    {
      "label": "note",
      "kind": 14,
      "detail": "snippet Note",
      "documentation": {
        "value": "Note directive"
      },
      "insertText": ".. note::\n\n   ${0}",
      "insertTextRules": 4,
      "sortText": "03_snip"
    }
  ]
}
