{
  "base": "vs",
  "inherit": true,
  "rules": [
    { "token": "", "foreground": "3d515c", "background": "f0f0f0" },
    { "token": "comment", "foreground": "90a0a8", "fontStyle": "italic" },
    { "token": "comment.block", "foreground": "90a0a8", "fontStyle": "italic" },
    { "token": "comment.line", "foreground": "90a0a8", "fontStyle": "italic" },
    { "token": "comment.doc", "foreground": "90a0a8", "fontStyle": "italic" },
    { "token": "comment.block.documentation", "foreground": "90a0a8", "fontStyle": "italic" },
    { "token": "punctuation.definition.comment", "foreground": "90a0a8", "fontStyle": "italic" },
    { "token": "keyword", "foreground": "c4956a", "fontStyle": "bold" },
    { "token": "keyword.control", "foreground": "c4956a", "fontStyle": "bold" },
    { "token": "keyword.operator", "foreground": "7060b0" },
    { "token": "keyword.operator.new", "foreground": "c4956a", "fontStyle": "bold" },
    { "token": "keyword.operator.expression", "foreground": "c4956a", "fontStyle": "bold" },
    { "token": "keyword.operator.logical", "foreground": "7060b0" },
    { "token": "keyword.operator.assignment", "foreground": "7060b0" },
    { "token": "keyword.operator.comparison", "foreground": "7060b0" },
    { "token": "keyword.other", "foreground": "c4956a", "fontStyle": "bold" },
    { "token": "keyword.flow", "foreground": "c4956a", "fontStyle": "bold" },
    { "token": "keyword.import", "foreground": "c4956a", "fontStyle": "bold" },
    { "token": "keyword.package", "foreground": "c4956a", "fontStyle": "bold" },
    { "token": "keyword.type", "foreground": "3d88c0", "fontStyle": "bold" },
    { "token": "keyword.control.flow", "foreground": "c4956a", "fontStyle": "bold" },
    { "token": "keyword.control.import", "foreground": "c4956a", "fontStyle": "bold" },
    { "token": "keyword.control.export", "foreground": "c4956a", "fontStyle": "bold" },
    { "token": "keyword.control.from", "foreground": "c4956a", "fontStyle": "bold" },
    { "token": "keyword.control.return", "foreground": "c4956a", "fontStyle": "bold" },
    { "token": "keyword.control.conditional", "foreground": "c4956a", "fontStyle": "bold" },
    { "token": "keyword.control.loop", "foreground": "c4956a", "fontStyle": "bold" },
    { "token": "keyword.control.trycatch", "foreground": "c4956a", "fontStyle": "bold" },
    { "token": "string", "foreground": "49916a" },
    { "token": "string.quoted", "foreground": "49916a" },
    { "token": "string.quoted.single", "foreground": "49916a" },
    { "token": "string.quoted.double", "foreground": "49916a" },
    { "token": "string.template", "foreground": "49916a" },
    { "token": "string.interpolated", "foreground": "49916a" },
    { "token": "string.regexp", "foreground": "49916a" },
    { "token": "string.escape", "foreground": "7060b0" },
    { "token": "string.key", "foreground": "c05050" },
    { "token": "string.key.json", "foreground": "3d88c0" },
    { "token": "string.value", "foreground": "49916a" },
    { "token": "string.value.json", "foreground": "49916a" },
    { "token": "string.unquoted", "foreground": "49916a" },
    { "token": "number", "foreground": "c05050" },
    { "token": "number.float", "foreground": "c05050" },
    { "token": "number.hex", "foreground": "c05050" },
    { "token": "number.octal", "foreground": "c05050" },
    { "token": "number.binary", "foreground": "c05050" },
    { "token": "constant", "foreground": "c05050" },
    { "token": "constant.language", "foreground": "c05050" },
    { "token": "constant.language.boolean", "foreground": "c05050" },
    { "token": "constant.language.boolean.true", "foreground": "c05050" },
    { "token": "constant.language.boolean.false", "foreground": "c05050" },
    { "token": "constant.language.null", "foreground": "c05050" },
    { "token": "constant.language.undefined", "foreground": "c05050" },
    { "token": "constant.numeric", "foreground": "c05050" },
    { "token": "constant.character", "foreground": "c05050" },
    { "token": "constant.character.escape", "foreground": "7060b0" },
    { "token": "constant.other", "foreground": "c05050" },
    { "token": "constant.other.color", "foreground": "c05050" },
    { "token": "constant.other.symbol", "foreground": "c05050" },
    { "token": "constant.regexp", "foreground": "49916a" },
    { "token": "variable", "foreground": "3d515c" },
    { "token": "variable.name", "foreground": "3d515c" },
    { "token": "variable.other", "foreground": "3d515c" },
    { "token": "variable.parameter", "foreground": "3d515c" },
    { "token": "variable.language", "foreground": "c4956a", "fontStyle": "bold" },
    { "token": "variable.language.this", "foreground": "c4956a", "fontStyle": "bold" },
    { "token": "variable.language.self", "foreground": "c4956a", "fontStyle": "bold" },
    { "token": "variable.language.super", "foreground": "c4956a", "fontStyle": "bold" },
    { "token": "variable.predefined", "foreground": "3d88c0" },
    { "token": "variable.other.readwrite", "foreground": "3d515c" },
    { "token": "variable.other.constant", "foreground": "c05050" },
    { "token": "variable.other.property", "foreground": "3d515c" },
    { "token": "variable.other.object", "foreground": "3d515c" },
    { "token": "identifier", "foreground": "3d515c" },
    { "token": "function", "foreground": "16826e" },
    { "token": "function.name", "foreground": "16826e" },
    { "token": "support.function", "foreground": "16826e" },
    { "token": "entity.name.function", "foreground": "16826e" },
    { "token": "entity.name.function.method", "foreground": "16826e" },
    { "token": "meta.function-call", "foreground": "16826e" },
    { "token": "meta.function-call.generic", "foreground": "16826e" },
    { "token": "type", "foreground": "3d88c0" },
    { "token": "type.identifier", "foreground": "3d88c0" },
    { "token": "type.primitive", "foreground": "3d88c0" },
    { "token": "support.type", "foreground": "3d88c0" },
    { "token": "support.type.primitive", "foreground": "3d88c0" },
    { "token": "support.type.builtin", "foreground": "3d88c0" },
    { "token": "support.type.property-name", "foreground": "3d515c" },
    { "token": "support.type.property-name.css", "foreground": "3d515c" },
    { "token": "support.type.exception", "foreground": "c05050" },
    { "token": "support.class", "foreground": "3d88c0" },
    { "token": "support.module", "foreground": "3d88c0" },
    { "token": "support.constant", "foreground": "c05050" },
    { "token": "support.variable", "foreground": "3d515c" },
    { "token": "support.other", "foreground": "3d515c" },
    { "token": "entity.name.type", "foreground": "3d88c0" },
    { "token": "entity.name.type.class", "foreground": "3d88c0" },
    { "token": "entity.name.type.interface", "foreground": "3d88c0" },
    { "token": "entity.name.type.enum", "foreground": "3d88c0" },
    { "token": "entity.name.type.module", "foreground": "3d88c0" },
    { "token": "entity.other.inherited-class", "foreground": "3d88c0", "fontStyle": "italic" },
    { "token": "entity.other.attribute-name", "foreground": "3d88c0" },
    { "token": "entity.other.attribute-name.html", "foreground": "3d88c0" },
    { "token": "entity.other.attribute-name.css", "foreground": "3d88c0" },
    { "token": "entity.other.attribute-name.class.css", "foreground": "3d88c0" },
    { "token": "entity.other.attribute-name.id.css", "foreground": "c4956a" },
    { "token": "entity.name.tag", "foreground": "c05050" },
    { "token": "entity.name.tag.html", "foreground": "c05050" },
    { "token": "entity.name.tag.xml", "foreground": "c05050" },
    { "token": "entity.name.tag.css", "foreground": "c05050" },
    { "token": "class", "foreground": "3d88c0" },
    { "token": "class.name", "foreground": "3d88c0" },
    { "token": "entity.name.class", "foreground": "3d88c0" },
    { "token": "storage", "foreground": "c4956a", "fontStyle": "bold" },
    { "token": "storage.type", "foreground": "c4956a", "fontStyle": "bold" },
    { "token": "storage.type.class", "foreground": "c4956a", "fontStyle": "bold" },
    { "token": "storage.type.function", "foreground": "c4956a", "fontStyle": "bold" },
    { "token": "storage.type.interface", "foreground": "c4956a", "fontStyle": "bold" },
    { "token": "storage.type.enum", "foreground": "c4956a", "fontStyle": "bold" },
    { "token": "storage.type.namespace", "foreground": "c4956a", "fontStyle": "bold" },
    { "token": "storage.type.property", "foreground": "c4956a", "fontStyle": "bold" },
    { "token": "storage.modifier", "foreground": "c4956a", "fontStyle": "bold" },
    { "token": "storage.modifier.async", "foreground": "c4956a", "fontStyle": "bold" },
    { "token": "storage.modifier.static", "foreground": "c4956a", "fontStyle": "bold" },
    { "token": "operator", "foreground": "7060b0" },
    { "token": "operators", "foreground": "7060b0" },
    { "token": "operator.assignment", "foreground": "7060b0" },
    { "token": "operator.arithmetic", "foreground": "7060b0" },
    { "token": "operator.comparison", "foreground": "7060b0" },
    { "token": "operator.logical", "foreground": "7060b0" },
    { "token": "operator.type", "foreground": "7060b0" },
    { "token": "punctuation", "foreground": "3d515c" },
    { "token": "punctuation.definition", "foreground": "3d515c" },
    { "token": "punctuation.definition.string", "foreground": "49916a" },
    { "token": "punctuation.definition.tag", "foreground": "c05050" },
    { "token": "punctuation.separator.key-value.css", "foreground": "3d515c" },
    { "token": "delimiter", "foreground": "3d515c" },
    { "token": "delimiter.bracket", "foreground": "3d515c" },
    { "token": "delimiter.parenthesis", "foreground": "3d515c" },
    { "token": "delimiter.square", "foreground": "3d515c" },
    { "token": "delimiter.curly", "foreground": "3d515c" },
    { "token": "delimiter.angle", "foreground": "3d515c" },
    { "token": "delimiter.comma", "foreground": "3d515c" },
    { "token": "delimiter.period", "foreground": "3d515c" },
    { "token": "delimiter.semicolon", "foreground": "3d515c" },
    { "token": "regexp", "foreground": "49916a" },
    { "token": "regexp.escape", "foreground": "7060b0" },
    { "token": "regexp.control", "foreground": "49916a" },
    { "token": "tag", "foreground": "c05050" },
    { "token": "tag.html", "foreground": "c05050" },
    { "token": "tag.xml", "foreground": "c05050" },
    { "token": "tag.id.pug", "foreground": "3d88c0" },
    { "token": "tag.class.pug", "foreground": "3d88c0" },
    { "token": "metatag", "foreground": "c05050" },
    { "token": "metatag.html", "foreground": "c05050" },
    { "token": "metatag.xml", "foreground": "c05050" },
    { "token": "metatag.content.html", "foreground": "49916a" },
    { "token": "metatag.php", "foreground": "c4956a" },
    { "token": "attribute.name", "foreground": "3d88c0" },
    { "token": "attribute.name.html", "foreground": "3d88c0" },
    { "token": "attribute.name.xml", "foreground": "3d88c0" },
    { "token": "attribute.value", "foreground": "49916a" },
    { "token": "attribute.value.html", "foreground": "49916a" },
    { "token": "attribute.value.xml", "foreground": "49916a" },
    { "token": "attribute.value.number", "foreground": "c05050" },
    { "token": "attribute.value.unit", "foreground": "c05050" },
    { "token": "annotation", "foreground": "a050a0" },
    { "token": "annotation.name", "foreground": "a050a0" },
    { "token": "decorator", "foreground": "a050a0" },
    { "token": "namespace", "foreground": "3d88c0" },
    { "token": "interface", "foreground": "3d88c0" },
    { "token": "enum", "foreground": "3d88c0" },
    { "token": "struct", "foreground": "3d88c0" },
    { "token": "label", "foreground": "c4956a" },
    { "token": "property", "foreground": "3d515c" },
    { "token": "meta.property-name", "foreground": "3d515c" },
    { "token": "meta.property-value", "foreground": "3d515c" },
    { "token": "meta.object-literal.key", "foreground": "3d88c0" },
    { "token": "meta.selector", "foreground": "c05050" },
    { "token": "meta.selector.css", "foreground": "c05050" },
    { "token": "meta.tag", "foreground": "c05050" },
    { "token": "meta.tag.html", "foreground": "c05050" },
    { "token": "meta.embedded", "foreground": "3d515c" },
    { "token": "meta.preprocessor", "foreground": "c4956a" },
    { "token": "meta.definition.variable", "foreground": "3d515c" },
    { "token": "meta.diff", "foreground": "90a0a8" },
    { "token": "meta.diff.header", "foreground": "3d88c0", "fontStyle": "bold" },
    { "token": "meta.structure.dictionary.json", "foreground": "3d515c" },
    { "token": "meta.structure.dictionary.key.json", "foreground": "3d88c0" },
    { "token": "meta.structure.dictionary.value.json", "foreground": "49916a" },
    { "token": "meta.structure.array.json", "foreground": "3d515c" },
    { "token": "meta.brace.round", "foreground": "3d515c" },
    { "token": "meta.brace.square", "foreground": "3d515c" },
    { "token": "meta.brace.curly", "foreground": "3d515c" },
    { "token": "meta.xml-processing", "foreground": "90a0a8" },
    { "token": "meta.sgml.html meta.doctype", "foreground": "90a0a8" },
    { "token": "markup.heading", "foreground": "c05050", "fontStyle": "bold" },
    { "token": "markup.heading.1", "foreground": "c05050", "fontStyle": "bold" },
    { "token": "markup.heading.2", "foreground": "c05050", "fontStyle": "bold" },
    { "token": "markup.heading.3", "foreground": "c4956a", "fontStyle": "bold" },
    { "token": "markup.bold", "fontStyle": "bold" },
    { "token": "markup.italic", "fontStyle": "italic" },
    { "token": "markup.underline", "fontStyle": "underline" },
    { "token": "markup.strikethrough", "fontStyle": "strikethrough" },
    { "token": "markup.inline.raw", "foreground": "49916a" },
    { "token": "markup.quote", "foreground": "90a0a8", "fontStyle": "italic" },
    { "token": "markup.list", "foreground": "c4956a" },
    { "token": "markup.list.numbered", "foreground": "c4956a" },
    { "token": "markup.list.unnumbered", "foreground": "c4956a" },
    { "token": "markup.inserted", "foreground": "49916a" },
    { "token": "markup.deleted", "foreground": "c05050" },
    { "token": "markup.changed", "foreground": "c4956a" },
    { "token": "markup.link", "foreground": "3d88c0", "fontStyle": "underline" },
    { "token": "markup.raw", "foreground": "49916a" },
    { "token": "markup.raw.block", "foreground": "49916a" },
    { "token": "invalid", "foreground": "c05050" },
    { "token": "invalid.illegal", "foreground": "c05050" },
    { "token": "invalid.deprecated", "foreground": "c05050", "fontStyle": "strikethrough" },
    { "token": "predefined", "foreground": "3d88c0" },
    { "token": "emphasis", "fontStyle": "italic" },
    { "token": "strong", "fontStyle": "bold" },
    { "token": "header", "foreground": "c05050", "fontStyle": "bold" },
    { "token": "key", "foreground": "3d88c0" },
    { "token": "key.json", "foreground": "3d88c0" },
    { "token": "builtin", "foreground": "16826e" },
    { "token": "constructor", "foreground": "16826e" },
    { "token": "selector", "foreground": "c05050" },
    { "token": "selector.class", "foreground": "3d88c0" },
    { "token": "selector.id", "foreground": "c4956a" },
    { "token": "selector.pseudo", "foreground": "a050a0" },
    { "token": "pseudo", "foreground": "a050a0" },
    { "token": "at-keyword", "foreground": "c4956a", "fontStyle": "bold" },
    { "token": "keyman", "foreground": "c4956a" },
    { "token": "keyman.keyword", "foreground": "c4956a", "fontStyle": "bold" },
    { "token": "keyman.string", "foreground": "49916a" },
    { "token": "keyman.comment", "foreground": "90a0a8", "fontStyle": "italic" },
    { "token": "keyman.number", "foreground": "c05050" },
    { "token": "keyman.operator", "foreground": "7060b0" }
  ],
  "colors": {
    "editor.background": "#f0f0f0",
    "editor.foreground": "#3d515c",
    "editor.lineHighlightBackground": "#e6eaed",
    "editor.lineHighlightBorder": "#dde2e6",
    "editor.selectionBackground": "#c0d4e4",
    "editor.selectionHighlightBackground": "#cddded",
    "editor.inactiveSelectionBackground": "#cddded80",
    "editor.wordHighlightBackground": "#cddded80",
    "editor.wordHighlightStrongBackground": "#c0d4e4aa",
    "editor.findMatchBackground": "#c4956a50",
    "editor.findMatchHighlightBackground": "#c4956a30",
    "editor.rangeHighlightBackground": "#e6eaed50",
    "editor.hoverHighlightBackground": "#c0d4e440",
    "editor.foldBackground": "#e6eaed80",
    "editorCursor.foreground": "#3d88c0",
    "editorWhitespace.foreground": "#c8cdd0",
    "editorIndentGuide.background": "#d8dcdf",
    "editorIndentGuide.activeBackground": "#b0b8bc",
    "editorLineNumber.foreground": "#a0aab0",
    "editorLineNumber.activeForeground": "#3d515c",
    "editorRuler.foreground": "#d8dcdf",
    "editorBracketMatch.background": "#c0d4e440",
    "editorBracketMatch.border": "#3d88c080",
    "editorBracketHighlight.foreground1": "#3d88c0",
    "editorBracketHighlight.foreground2": "#a050a0",
    "editorBracketHighlight.foreground3": "#c4956a",
    "editorBracketHighlight.foreground4": "#49916a",
    "editorBracketHighlight.foreground5": "#c05050",
    "editorBracketHighlight.foreground6": "#7060b0",
    "editorOverviewRuler.border": "#d8dcdf",
    "editorOverviewRuler.errorForeground": "#c05050",
    "editorOverviewRuler.warningForeground": "#c4956a",
    "editorOverviewRuler.infoForeground": "#3d88c0",
    "editorOverviewRuler.findMatchForeground": "#c4956a50",
    "editorOverviewRuler.selectionHighlightForeground": "#c0d4e4",
    "editorError.foreground": "#c05050",
    "editorWarning.foreground": "#c4956a",
    "editorInfo.foreground": "#3d88c0",
    "editorHint.foreground": "#90a0a8",
    "editorGutter.background": "#f0f0f0",
    "editorGutter.modifiedBackground": "#3d88c0",
    "editorGutter.addedBackground": "#49916a",
    "editorGutter.deletedBackground": "#c05050",
    "editorWidget.background": "#e6eaed",
    "editorWidget.border": "#c8cdd0",
    "editorWidget.foreground": "#3d515c",
    "editorSuggestWidget.background": "#f0f0f0",
    "editorSuggestWidget.border": "#c8cdd0",
    "editorSuggestWidget.foreground": "#3d515c",
    "editorSuggestWidget.highlightForeground": "#3d88c0",
    "editorSuggestWidget.selectedBackground": "#c0d4e4",
    "editorHoverWidget.background": "#e6eaed",
    "editorHoverWidget.border": "#c8cdd0",
    "peekView.border": "#3d88c0",
    "peekViewEditor.background": "#e6eaed",
    "peekViewResult.background": "#e6eaed",
    "peekViewTitle.background": "#dde2e6",
    "diffEditor.insertedTextBackground": "#49916a20",
    "diffEditor.removedTextBackground": "#c0505020",
    "minimap.findMatchHighlight": "#c4956a50",
    "minimap.selectionHighlight": "#c0d4e4",
    "minimap.errorHighlight": "#c05050",
    "minimap.warningHighlight": "#c4956a",
    "minimapGutter.addedBackground": "#49916a",
    "minimapGutter.modifiedBackground": "#3d88c0",
    "minimapGutter.deletedBackground": "#c05050",
    "sideBar.background": "#e6eaed",
    "sideBar.foreground": "#3d515c",
    "sideBar.border": "#d8dcdf",
    "sideBarTitle.foreground": "#3d515c",
    "sideBarSectionHeader.background": "#dde2e6",
    "sideBarSectionHeader.foreground": "#3d515c",
    "list.activeSelectionBackground": "#c0d4e4",
    "list.activeSelectionForeground": "#3d515c",
    "list.hoverBackground": "#dde2e6",
    "list.highlightForeground": "#3d88c0",
    "list.inactiveSelectionBackground": "#cddded",
    "statusBar.background": "#3d88c0",
    "statusBar.foreground": "#ffffff",
    "statusBar.border": "#3d88c0",
    "statusBar.debuggingBackground": "#c05050",
    "statusBar.debuggingForeground": "#ffffff",
    "statusBar.noFolderBackground": "#7060b0",
    "statusBar.noFolderForeground": "#ffffff",
    "statusBarItem.hoverBackground": "#2d6fa0",
    "statusBarItem.activeBackground": "#245d88",
    "titleBar.activeBackground": "#dde2e6",
    "titleBar.activeForeground": "#3d515c",
    "titleBar.inactiveBackground": "#e6eaed",
    "titleBar.inactiveForeground": "#90a0a8",
    "titleBar.border": "#d8dcdf",
    "tab.activeBackground": "#f0f0f0",
    "tab.activeForeground": "#3d515c",
    "tab.inactiveBackground": "#e6eaed",
    "tab.inactiveForeground": "#90a0a8",
    "tab.border": "#d8dcdf",
    "tab.activeBorder": "#3d88c0",
    "tab.hoverBackground": "#f0f0f0",
    "tab.unfocusedActiveBorder": "#90a0a8",
    "activityBar.background": "#dde2e6",
    "activityBar.foreground": "#3d515c",
    "activityBar.border": "#d8dcdf",
    "activityBar.activeBorder": "#3d88c0",
    "activityBarBadge.background": "#3d88c0",
    "activityBarBadge.foreground": "#ffffff",
    "panel.background": "#e6eaed",
    "panel.border": "#d8dcdf",
    "panelTitle.activeBorder": "#3d88c0",
    "panelTitle.activeForeground": "#3d515c",
    "panelTitle.inactiveForeground": "#90a0a8",
    "input.background": "#ffffff",
    "input.foreground": "#3d515c",
    "input.border": "#c8cdd0",
    "input.placeholderForeground": "#90a0a8",
    "inputOption.activeBorder": "#3d88c0",
    "dropdown.background": "#ffffff",
    "dropdown.foreground": "#3d515c",
    "dropdown.border": "#c8cdd0",
    "button.background": "#3d88c0",
    "button.foreground": "#ffffff",
    "button.hoverBackground": "#2d6fa0",
    "badge.background": "#3d88c0",
    "badge.foreground": "#ffffff",
    "scrollbar.shadow": "#00000015",
    "scrollbarSlider.background": "#b0b8bc50",
    "scrollbarSlider.hoverBackground": "#90a0a870",
    "scrollbarSlider.activeBackground": "#70808890",
    "breadcrumb.foreground": "#90a0a8",
    "breadcrumb.focusForeground": "#3d515c",
    "breadcrumb.activeSelectionForeground": "#3d88c0",
    "terminal.ansiBlack": "#3d515c",
    "terminal.ansiRed": "#c05050",
    "terminal.ansiGreen": "#49916a",
    "terminal.ansiYellow": "#c4956a",
    "terminal.ansiBlue": "#3d88c0",
    "terminal.ansiMagenta": "#a050a0",
    "terminal.ansiCyan": "#3d88c0",
    "terminal.ansiWhite": "#f0f0f0",
    "terminal.ansiBrightBlack": "#90a0a8",
    "terminal.ansiBrightRed": "#c05050",
    "terminal.ansiBrightGreen": "#49916a",
    "terminal.ansiBrightYellow": "#c4956a",
    "terminal.ansiBrightBlue": "#3d88c0",
    "terminal.ansiBrightMagenta": "#a050a0",
    "terminal.ansiBrightCyan": "#3d88c0",
    "terminal.ansiBrightWhite": "#ffffff",
    "terminal.foreground": "#3d515c",
    "terminal.background": "#f0f0f0",
    "gitDecoration.modifiedResourceForeground": "#3d88c0",
    "gitDecoration.deletedResourceForeground": "#c05050",
    "gitDecoration.untrackedResourceForeground": "#49916a",
    "gitDecoration.conflictingResourceForeground": "#c4956a",
    "gitDecoration.ignoredResourceForeground": "#90a0a8"
  }
}