{
  "base": "vs-dark",
  "inherit": true,
  "rules": [
    { "token": "", "foreground": "e0def4", "background": "191724" },
    { "token": "comment", "foreground": "6e6a86", "fontStyle": "italic" },
    { "token": "comment.line", "foreground": "6e6a86", "fontStyle": "italic" },
    { "token": "comment.block", "foreground": "6e6a86", "fontStyle": "italic" },
    { "token": "comment.doc", "foreground": "908caa", "fontStyle": "italic" },
    { "token": "keyword", "foreground": "31748f" },
    { "token": "keyword.control", "foreground": "31748f" },
    { "token": "keyword.operator", "foreground": "908caa" },
    { "token": "keyword.other", "foreground": "31748f" },
    { "token": "keyword.json", "foreground": "31748f" },
    { "token": "string", "foreground": "f6c177" },
    { "token": "string.quoted", "foreground": "f6c177" },
    { "token": "string.template", "foreground": "f6c177" },
    { "token": "string.regexp", "foreground": "eb6f92" },
    { "token": "string.escape", "foreground": "c4a7e7" },
    { "token": "string.invalid", "foreground": "eb6f92" },
    { "token": "string.quote", "foreground": "f6c177" },
    { "token": "string.key.json", "foreground": "9ccfd8" },
    { "token": "string.value.json", "foreground": "f6c177" },
    { "token": "number", "foreground": "ebbcba" },
    { "token": "number.hex", "foreground": "ebbcba" },
    { "token": "number.octal", "foreground": "ebbcba" },
    { "token": "regexp", "foreground": "eb6f92" },
    { "token": "operator", "foreground": "908caa" },
    { "token": "delimiter", "foreground": "6e6a86" },
    { "token": "delimiter.html", "foreground": "6e6a86" },
    { "token": "delimiter.xml", "foreground": "6e6a86" },
    { "token": "identifier", "foreground": "e0def4" },
    { "token": "type", "foreground": "9ccfd8" },
    { "token": "type.identifier", "foreground": "9ccfd8" },
    { "token": "class", "foreground": "9ccfd8" },
    { "token": "function", "foreground": "ebbcba" },
    { "token": "variable", "foreground": "e0def4" },
    { "token": "variable.predefined", "foreground": "eb6f92" },
    { "token": "variable.other", "foreground": "e0def4" },
    { "token": "constant", "foreground": "f6c177" },
    { "token": "constant.numeric", "foreground": "ebbcba" },
    { "token": "constant.language", "foreground": "31748f" },
    { "token": "constant.character", "foreground": "9ccfd8" },
    { "token": "constant.character.escape", "foreground": "c4a7e7" },
    { "token": "constant.other", "foreground": "f6c177" },
    { "token": "tag", "foreground": "eb6f92" },
    { "token": "attribute.name", "foreground": "c4a7e7" },
    { "token": "attribute.value", "foreground": "f6c177" },
    { "token": "invalid", "foreground": "eb6f92" },
    { "token": "namespace", "foreground": "31748f" },
    { "token": "enum", "foreground": "9ccfd8" },
    { "token": "interface", "foreground": "9ccfd8" },
    { "token": "struct", "foreground": "9ccfd8" },
    { "token": "typeParameter", "foreground": "c4a7e7" },
    { "token": "parameter", "foreground": "c4a7e7" },
    { "token": "property", "foreground": "9ccfd8" },
    { "token": "enumMember", "foreground": "ebbcba" },
    { "token": "event", "foreground": "f6c177" },
    { "token": "method", "foreground": "ebbcba" },
    { "token": "macro", "foreground": "31748f" },
    { "token": "decorator", "foreground": "c4a7e7" },
    { "token": "modifier", "foreground": "31748f" },
    { "token": "storage", "foreground": "31748f" },
    { "token": "storage.type", "foreground": "31748f" },
    { "token": "storage.modifier", "foreground": "31748f" },
    { "token": "support.function", "foreground": "ebbcba" },
    { "token": "support.type", "foreground": "9ccfd8" },
    { "token": "support.class", "foreground": "9ccfd8" },
    { "token": "support.variable", "foreground": "e0def4" },
    { "token": "entity.name.function", "foreground": "ebbcba" },
    { "token": "entity.name.type", "foreground": "9ccfd8" },
    { "token": "entity.name.class", "foreground": "9ccfd8" },
    { "token": "entity.name.tag", "foreground": "eb6f92" },
    { "token": "markup.heading", "foreground": "31748f", "fontStyle": "bold" },
    { "token": "markup.bold", "foreground": "f6c177", "fontStyle": "bold" },
    { "token": "markup.italic", "foreground": "eb6f92", "fontStyle": "italic" },
    { "token": "markup.underline", "foreground": "e0def4", "fontStyle": "underline" },
    { "token": "markup.strikethrough", "foreground": "908caa", "fontStyle": "strikethrough" },
    { "token": "markup.inline.raw", "foreground": "f6c177" },
    { "token": "markup.list", "foreground": "eb6f92" },
    { "token": "markup.quote", "foreground": "6e6a86", "fontStyle": "italic" },
    { "token": "meta.embedded", "foreground": "e0def4" },
    { "token": "meta.tag", "foreground": "eb6f92" },
    { "token": "meta.selector", "foreground": "c4a7e7" },
    { "token": "punctuation.definition", "foreground": "6e6a86" },
    { "token": "metatag", "foreground": "6e6a86" },
    { "token": "metatag.html", "foreground": "6e6a86" },
    { "token": "metatag.xml", "foreground": "6e6a86" },
    { "token": "metatag.content.html", "foreground": "e0def4" },
    { "token": "key", "foreground": "9ccfd8" },
    { "token": "annotation", "foreground": "f6c177" },
    { "token": "bracket", "foreground": "6e6a86" },
    { "token": "white", "foreground": "26233a" }
  ],
  "colors": {
    "editor.foreground": "#e0def4",
    "editor.background": "#191724",
    "editor.selectionBackground": "#403d52",
    "editor.inactiveSelectionBackground": "#403d5280",
    "editor.selectionHighlightBackground": "#403d5280",
    "editor.lineHighlightBackground": "#21202e",
    "editor.lineHighlightBorder": "#21202e00",
    "editorCursor.foreground": "#ebbcba",
    "editorWhitespace.foreground": "#26233a",
    "editorIndentGuide.background": "#26233a",
    "editorIndentGuide.activeBackground": "#6e6a86",
    "editorBracketMatch.background": "#524f6780",
    "editorBracketMatch.border": "#c4a7e7",
    "editorLineNumber.foreground": "#6e6a86",
    "editorLineNumber.activeForeground": "#e0def4",
    "editorGutter.background": "#191724",
    "editorGutter.modifiedBackground": "#31748f",
    "editorGutter.addedBackground": "#9ccfd8",
    "editorGutter.deletedBackground": "#eb6f92",
    "editorOverviewRuler.border": "#26233a",
    "editorOverviewRuler.errorForeground": "#eb6f92",
    "editorOverviewRuler.warningForeground": "#f6c177",
    "editorOverviewRuler.infoForeground": "#9ccfd8",
    "editorError.foreground": "#eb6f92",
    "editorWarning.foreground": "#f6c177",
    "editorInfo.foreground": "#9ccfd8",
    "editorHint.foreground": "#c4a7e7",
    "editorWidget.background": "#1f1d2e",
    "editorWidget.border": "#26233a",
    "editorWidget.foreground": "#e0def4",
    "editorSuggestWidget.background": "#1f1d2e",
    "editorSuggestWidget.border": "#26233a",
    "editorSuggestWidget.foreground": "#e0def4",
    "editorSuggestWidget.highlightForeground": "#9ccfd8",
    "editorSuggestWidget.selectedBackground": "#403d52",
    "editorHoverWidget.background": "#1f1d2e",
    "editorHoverWidget.border": "#26233a",
    "editorHoverWidget.foreground": "#e0def4",
    "peekView.border": "#c4a7e7",
    "peekViewEditor.background": "#1f1d2e",
    "peekViewEditor.matchHighlightBackground": "#403d5280",
    "peekViewResult.background": "#191724",
    "peekViewResult.fileForeground": "#e0def4",
    "peekViewResult.lineForeground": "#908caa",
    "peekViewResult.matchHighlightBackground": "#403d5280",
    "peekViewResult.selectionBackground": "#403d52",
    "peekViewResult.selectionForeground": "#e0def4",
    "peekViewTitle.background": "#26233a",
    "peekViewTitleDescription.foreground": "#908caa",
    "peekViewTitleLabel.foreground": "#e0def4",
    "minimap.background": "#191724",
    "minimap.foregroundOpacity": "#000000cc",
    "minimap.selectionHighlight": "#403d52",
    "minimap.errorHighlight": "#eb6f92",
    "minimap.warningHighlight": "#f6c177",
    "minimap.findMatchHighlight": "#f6c17766",
    "minimapGutter.addedBackground": "#9ccfd8",
    "minimapGutter.modifiedBackground": "#31748f",
    "minimapGutter.deletedBackground": "#eb6f92",
    "input.background": "#26233a",
    "input.foreground": "#e0def4",
    "input.border": "#524f67",
    "input.placeholderForeground": "#6e6a86",
    "inputOption.activeBorder": "#c4a7e7",
    "dropdown.background": "#26233a",
    "dropdown.foreground": "#e0def4",
    "dropdown.border": "#524f67",
    "focusBorder": "#c4a7e780",
    "foreground": "#e0def4",
    "scrollbar.shadow": "#19172400",
    "scrollbarSlider.background": "#403d5266",
    "scrollbarSlider.hoverBackground": "#403d5299",
    "scrollbarSlider.activeBackground": "#403d52cc"
  }
}