{
  "language": "nestjs",
  "symbolPatterns": [
    {
      "name": "ControllerClass",
      "pattern": "@Controller\\s*\\([^)]*\\)\\s*(?:export\\s+)?class\\s+([A-Za-z][a-zA-Z0-9]*Controller)",
      "captureGroup": 1,
      "kind": 4,
      "detail": "NestJS Controller"
    },
    {
      "name": "InjectableService",
      "pattern": "@Injectable\\s*\\(\\)\\s*(?:export\\s+)?class\\s+([A-Za-z][a-zA-Z0-9]*Service)",
      "captureGroup": 1,
      "kind": 4,
      "detail": "NestJS Injectable Service"
    },
    {
      "name": "ModuleClass",
      "pattern": "@Module\\s*\\([\\s\\S]*?\\)\\s*(?:export\\s+)?class\\s+([A-Za-z][a-zA-Z0-9]*Module)",
      "captureGroup": 1,
      "kind": 1,
      "detail": "NestJS Module"
    },
    {
      "name": "GetHandler",
      "pattern": "@Get\\s*\\([^)]*\\)\\s*(?:@[\\w]+\\s*\\([^)]*\\)\\s*)*(?:async\\s+)?([a-zA-Z][a-zA-Z0-9]*)\\s*\\(",
      "captureGroup": 1,
      "kind": 5,
      "detail": "GET route handler"
    },
    {
      "name": "PostHandler",
      "pattern": "@Post\\s*\\([^)]*\\)\\s*(?:@[\\w]+\\s*\\([^)]*\\)\\s*)*(?:async\\s+)?([a-zA-Z][a-zA-Z0-9]*)\\s*\\(",
      "captureGroup": 1,
      "kind": 5,
      "detail": "POST route handler"
    },
    {
      "name": "PutHandler",
      "pattern": "@Put\\s*\\([^)]*\\)\\s*(?:@[\\w]+\\s*\\([^)]*\\)\\s*)*(?:async\\s+)?([a-zA-Z][a-zA-Z0-9]*)\\s*\\(",
      "captureGroup": 1,
      "kind": 5,
      "detail": "PUT route handler"
    },
    {
      "name": "PatchHandler",
      "pattern": "@Patch\\s*\\([^)]*\\)\\s*(?:@[\\w]+\\s*\\([^)]*\\)\\s*)*(?:async\\s+)?([a-zA-Z][a-zA-Z0-9]*)\\s*\\(",
      "captureGroup": 1,
      "kind": 5,
      "detail": "PATCH route handler"
    },
    {
      "name": "DeleteHandler",
      "pattern": "@Delete\\s*\\([^)]*\\)\\s*(?:@[\\w]+\\s*\\([^)]*\\)\\s*)*(?:async\\s+)?([a-zA-Z][a-zA-Z0-9]*)\\s*\\(",
      "captureGroup": 1,
      "kind": 5,
      "detail": "DELETE route handler"
    },
    {
      "name": "GuardClass",
      "pattern": "@Injectable\\s*\\(\\)\\s*(?:export\\s+)?class\\s+([A-Za-z][a-zA-Z0-9]*Guard)\\s+implements\\s+CanActivate",
      "captureGroup": 1,
      "kind": 4,
      "detail": "NestJS Guard"
    },
    {
      "name": "PipeClass",
      "pattern": "@Injectable\\s*\\(\\)\\s*(?:export\\s+)?class\\s+([A-Za-z][a-zA-Z0-9]*Pipe)\\s+implements\\s+PipeTransform",
      "captureGroup": 1,
      "kind": 4,
      "detail": "NestJS Pipe"
    },
    {
      "name": "InterceptorClass",
      "pattern": "@Injectable\\s*\\(\\)\\s*(?:export\\s+)?class\\s+([A-Za-z][a-zA-Z0-9]*Interceptor)\\s+implements\\s+NestInterceptor",
      "captureGroup": 1,
      "kind": 4,
      "detail": "NestJS Interceptor"
    },
    {
      "name": "ExceptionFilter",
      "pattern": "@Catch\\s*\\([^)]*\\)\\s*(?:export\\s+)?class\\s+([A-Za-z][a-zA-Z0-9]*Filter)\\s+implements\\s+ExceptionFilter",
      "captureGroup": 1,
      "kind": 4,
      "detail": "NestJS Exception Filter"
    },
    {
      "name": "WebSocketGateway",
      "pattern": "@WebSocketGateway\\s*\\([^)]*\\)\\s*(?:export\\s+)?class\\s+([A-Za-z][a-zA-Z0-9]*Gateway)",
      "captureGroup": 1,
      "kind": 4,
      "detail": "NestJS WebSocket Gateway"
    },
    {
      "name": "MiddlewareClass",
      "pattern": "@Injectable\\s*\\(\\)\\s*(?:export\\s+)?class\\s+([A-Za-z][a-zA-Z0-9]*Middleware)\\s+implements\\s+NestMiddleware",
      "captureGroup": 1,
      "kind": 4,
      "detail": "NestJS Middleware"
    },
    {
      "name": "Interface",
      "pattern": "(?:export\\s+)?interface\\s+([A-Z][a-zA-Z0-9]*)",
      "captureGroup": 1,
      "kind": 10,
      "detail": "TypeScript interface"
    },
    {
      "name": "Enum",
      "pattern": "(?:export\\s+)?enum\\s+([A-Z][a-zA-Z0-9]*)",
      "captureGroup": 1,
      "kind": 9,
      "detail": "TypeScript enum"
    },
    {
      "name": "TypeAlias",
      "pattern": "(?:export\\s+)?type\\s+([A-Z][a-zA-Z0-9]*)\\s*=",
      "captureGroup": 1,
      "kind": 14,
      "detail": "TypeScript type alias"
    },
    {
      "name": "ConstantDeclaration",
      "pattern": "(?:export\\s+)?const\\s+([A-Z][A-Z0-9_]+)\\s*=",
      "captureGroup": 1,
      "kind": 13,
      "detail": "Constant declaration"
    },
    {
      "name": "EntityClass",
      "pattern": "@Entity\\s*\\([^)]*\\)\\s*(?:export\\s+)?class\\s+([A-Za-z][a-zA-Z0-9]*)",
      "captureGroup": 1,
      "kind": 4,
      "detail": "TypeORM Entity"
    },
    {
      "name": "DtoClass",
      "pattern": "(?:export\\s+)?class\\s+([A-Za-z][a-zA-Z0-9]*Dto)",
      "captureGroup": 1,
      "kind": 4,
      "detail": "Data Transfer Object"
    },
    {
      "name": "UseGuardsDecorator",
      "pattern": "@UseGuards\\s*\\(([A-Za-z][a-zA-Z0-9]*)\\)",
      "captureGroup": 1,
      "kind": 11,
      "detail": "Applied Guard"
    }
  ]
}