{
  "name": "pandoc",
  "description": "Universal document converter",
  "category": "media",
  "platforms": [
    "linux",
    "macos",
    "windows"
  ],
  "shells": [
    "bash",
    "zsh",
    "fish",
    "powershell"
  ],
  "subcommands": [],
  "globalOptions": [
    {
      "name": "-f",
      "description": "Input format",
      "type": "string"
    },
    {
      "name": "-t",
      "description": "Output format",
      "type": "string"
    },
    {
      "name": "-o",
      "description": "Output file",
      "type": "file"
    },
    {
      "name": "-s",
      "description": "Standalone document"
    },
    {
      "name": "--toc",
      "description": "Include table of contents"
    },
    {
      "name": "--template",
      "description": "Custom template",
      "type": "file"
    },
    {
      "name": "--css",
      "description": "CSS stylesheet",
      "type": "file"
    },
    {
      "name": "--metadata",
      "description": "Set metadata",
      "type": "string"
    },
    {
      "name": "--filter",
      "description": "JSON filter",
      "type": "string"
    },
    {
      "name": "--lua-filter",
      "description": "Lua filter",
      "type": "file"
    },
    {
      "name": "--reference-doc",
      "description": "Reference document for styling",
      "type": "file"
    },
    {
      "name": "--pdf-engine",
      "description": "PDF engine (xelatex, wkhtmltopdf, etc.)",
      "type": "string"
    },
    {
      "name": "--highlight-style",
      "description": "Syntax highlight theme",
      "type": "string"
    },
    {
      "name": "--number-sections",
      "description": "Number section headings"
    }
  ],
  "examples": [
    "pandoc README.md -o readme.pdf",
    "pandoc input.md -t html -s -o output.html",
    "pandoc input.md -t docx -o output.docx",
    "pandoc -f latex -t markdown input.tex -o output.md",
    "pandoc --toc -s input.md -o output.html",
    "pandoc input.md --pdf-engine=xelatex -o output.pdf"
  ],
  "relatedCommands": [
    "latex",
    "markdown",
    "asciidoctor",
    "groff"
  ]
}
